{"cameraMode":{"drawMode":0,"name":"Shaded","section":"Shading Mode"},"sceneLighting":true,"audioPlay":false,"sceneViewState":{"showFog":true,"showMaterialUpdate":false,"showSkybox":true,"showFlares":true,"showImageEffects":true,"showParticleSystems":true},"in2DMode":false,"pivot":{"x":13.688384056091309,"y":-59.21388626098633,"z":-15.022811889648438},"rotation":{"x":-0.010943155735731125,"y":0.9025493860244751,"z":-0.42983338236808779,"w":-0.022981300950050355},"size":140.67420959472657,"orthographic":false}